            {
                "employeeCountRange": {
                    "code": "C",
                    "name": "11-50"
                },
                "name": "Jaguar Land Rover \u201eDe Uiver\u201d",
                "websiteUrl": "www.deuiver.eu"
            },
            {
                "employeeCountRange": {
                    "code": "C",
                    "name": "11-50"
                },
                "name": "Jaguar Land Rover Sverige",
                "websiteUrl": "https://www.jaguar.se"
            },
            {
                "employeeCountRange": {
                    "code": "C",
                    "name": "11-50"
                },
                "name": "Jaguar Land Group Ltd.",
                "websiteUrl": "http://www.jaguarland.ca/"
            },
            {
                "employeeCountRange": {
                    "code": "C",
                    "name": "11-50"
                },
                "name": "Jaguar Energy Inc"
            },
            {
                "employeeCountRange": {
                    "code": "E",
                    "name": "201-500"
                },
                "name": "Jaguar Ingenieros Constructores S.A. de C.V.",
                "websiteUrl": "http://www.jaguaringenieros.com.mx/"
            },
            {
                "employeeCountRange": {
                    "code": "B",
                    "name": "2-10"
                },
                "name": "Jaguar Films",
                "websiteUrl": "www.jaguarfilms.net"
            },
            {
                "employeeCountRange": {
                    "code": "B",
                    "name": "2-10"
                },
                "name": "Jaguar Capital Inc.",
                "websiteUrl": "www.jaguarcapital.ca"
            },
            {
                "employeeCountRange": {
                    "code": "D",
                    "name": "51-200"
                },
                "name": "Jaguar Overseas Limited",
                "websiteUrl": "https://www.jaguaroverseas.com"
            },
            {
                "employeeCountRange": {
                    "code": "C",
                    "name": "11-50"
                },
                "name": "Jaguar Consultants",
                "websiteUrl": "www.jaguarconsultants.in"
            },
            {
                "employeeCountRange": {
                    "code": "B",
                    "name": "2-10"
                },
                "name": "Jaguar staffing solutions",
                "websiteUrl": "www.jaguarstaffing.com"
            },
            {
                "employeeCountRange": {
                    "code": "C",
                    "name": "11-50"
                },
                "name": "Jaguar Land Rover Diplomatic",
                "websiteUrl": "www.jaguarlandroverdiplomatic.com"
            },
            {
                "employeeCountRange": {
                    "code": "D",
                    "name": "51-200"
                },
                "name": "Jaguar Land Rover Mainline",
                "websiteUrl": "http://www.lrjagmainline.com"
            },
            {
                "employeeCountRange": {
                    "code": "C",
                    "name": "11-50"
                },
                "name": "Jaguar Land Rover Singapore",
                "websiteUrl": "http://www.jaguarlandrover.com"
            },
            {
                "employeeCountRange": {
                    "code": "C",
                    "name": "11-50"
                },
                "name": "Jaguar Saltwind Motor",
                "websiteUrl": "saltwindlandrover.es/"
            },
            {
                "employeeCountRange": {
                    "code": "C",
                    "name": "11-50"
                },
                "name": "Jaguar Land Rover Saskatoon",
                "websiteUrl": "jaguarsaskatoon.com"
            },
            {
                "employeeCountRange": {
                    "code": "C",
                    "name": "11-50"
                },
                "name": "Jaguar Design Studio",
                "websiteUrl": "http://www.jaguardesignstudio.com/"
            },
            {
                "name": "Jaguar Land Rover M\u00e9xico"
            },
            {
                "employeeCountRange": {
                    "code": "C",
                    "name": "11-50"
                },
                "name": "Jaguar Land Rover BIDAUD P\u00e8re et Fils",
                "websiteUrl": "http://www.bidaud.fr/"
            },
            {
                "employeeCountRange": {
                    "code": "C",
                    "name": "11-50"
                },
                "name": "Jaguar Academy of Sport",
                "websiteUrl": "www.jaguaracademyofsport.com"
            },
            {
                "employeeCountRange": {
                    "code": "C",
                    "name": "11-50"
                },
                "name": "Jaguar Land Rover Norge",
                "websiteUrl": "https://www.jaguar.no"
            },
